template_rmldist/__init__.py
template_rmldist-0.3.2.dist-info/METADATA
template_rmldist-0.3.2.dist-info/WHEEL
template_rmldist-0.3.2.dist-info/RECORD
