Metadata-Version: 2.1
Name: template-rmldist
Version: 0.3.2
Summary: This is the best Python package ever created!
Author: Jackson Rico
Author-email: jacksonrico@gmail.com
Requires-Python: >=3.10,<4.0
Classifier: Programming Language :: Python :: 3
Classifier: Programming Language :: Python :: 3.10
Classifier: Programming Language :: Python :: 3.11
Requires-Dist: rich (>=13.7.1,<14.0.0)
